{
  "info": {
    "description": "Dataset de ejemplo con gato y pájaro",
    "url": "http://ejemplo.com",
    "version": "1.0",
    "year": 2024,
    "contributor": "ejemplo",
    "date_created": "2024-06-23"
  },
  "licenses": [
    {
      "id": 1,
      "name": "Licencia de ejemplo",
      "url": "http://ejemplo.com/licencia"
    }
  ],
  "images": [
    {"id": 0, "file_name": "imagen1.jpg", "height": 480, "width": 640, "date_captured": "2024-06-23"},
    {"id": 1, "file_name": "imagen2.jpg", "height": 480, "width": 640, "date_captured": "2024-06-23"},
    {"id": 2, "file_name": "imagen3.jpg", "height": 480, "width": 640, "date_captured": "2024-06-23"},
    {"id": 3, "file_name": "imagen4.jpg", "height": 480, "width": 640, "date_captured": "2024-06-23"},
    {"id": 4, "file_name": "imagen5.jpg", "height": 480, "width": 640, "date_captured": "2024-06-23"},
    {"id": 5, "file_name": "imagen6.jpg", "height": 480, "width": 640, "date_captured": "2024-06-23"},
    {"id": 6, "file_name": "imagen7.jpg", "height": 480, "width": 640, "date_captured": "2024-06-23"},
    {"id": 7, "file_name": "imagen8.jpg", "height": 480, "width": 640, "date_captured": "2024-06-23"},
    {"id": 8, "file_name": "imagen9.jpg", "height": 480, "width": 640, "date_captured": "2024-06-23"},
    {"id": 9, "file_name": "imagen10.jpg", "height": 480, "width": 640, "date_captured": "2024-06-23"}
  ],
  "annotations": [
    {"id": 0, "image_id": 0, "category_id": 1, "bbox": [10, 20, 30, 40], "area": 1200, "iscrowd": 0},
    {"id": 1, "image_id": 0, "category_id": 2, "bbox": [50, 60, 30, 40], "area": 1200, "iscrowd": 0},
    {"id": 2, "image_id": 1, "category_id": 1, "bbox": [10, 20, 30, 40], "area": 1200, "iscrowd": 0},
    {"id": 3, "image_id": 1, "category_id": 2, "bbox": [50, 60, 30, 40], "area": 1200, "iscrowd": 0},
    {"id": 4, "image_id": 2, "category_id": 1, "bbox": [10, 20, 30, 40], "area": 1200, "iscrowd": 0},
    {"id": 5, "image_id": 2, "category_id": 2, "bbox": [50, 60, 30, 40], "area": 1200, "iscrowd": 0},
    {"id": 6, "image_id": 3, "category_id": 1, "bbox": [10, 20, 30, 40], "area": 1200, "iscrowd": 0},
    {"id": 7, "image_id": 3, "category_id": 2, "bbox": [50, 60, 30, 40], "area": 1200, "iscrowd": 0},
    {"id": 8, "image_id": 4, "category_id": 1, "bbox": [10, 20, 30, 40], "area": 1200, "iscrowd": 0},
    {"id": 9, "image_id": 4, "category_id": 2, "bbox": [50, 60, 30, 40], "area": 1200, "iscrowd": 0},
    {"id": 10, "image_id": 5, "category_id": 1, "bbox": [10, 20, 30, 40], "area": 1200, "iscrowd": 0},
    {"id": 11, "image_id": 5, "category_id": 2, "bbox": [50, 60, 30, 40], "area": 1200, "iscrowd": 0},
    {"id": 12, "image_id": 6, "category_id": 1, "bbox": [10, 20, 30, 40], "area": 1200, "iscrowd": 0},
    {"id": 13, "image_id": 6, "category_id": 2, "bbox": [50, 60, 30, 40], "area": 1200, "iscrowd": 0},
    {"id": 14, "image_id": 7, "category_id": 1, "bbox": [10, 20, 30, 40], "area": 1200, "iscrowd": 0},
    {"id": 15, "image_id": 7, "category_id": 2, "bbox": [50, 60, 30, 40], "area": 1200, "iscrowd": 0},
    {"id": 16, "image_id": 8, "category_id": 1, "bbox": [10, 20, 30, 40], "area": 1200, "iscrowd": 0},
    {"id": 17, "image_id": 8, "category_id": 2, "bbox": [50, 60, 30, 40], "area": 1200, "iscrowd": 0},
    {"id": 18, "image_id": 9, "category_id": 1, "bbox": [10, 20, 30, 40], "area": 1200, "iscrowd": 0},
    {"id": 19, "image_id": 9, "category_id": 2, "bbox": [50, 60, 30, 40], "area": 1200, "iscrowd": 0}
  ],
  "categories": [
    {"id": 1, "name": "gato", "supercategory": "animal"},
    {"id": 2, "name": "pájaro", "supercategory": "animal"}
  ]
}
